setup.py
django_serializers.egg-info/PKG-INFO
django_serializers.egg-info/SOURCES.txt
django_serializers.egg-info/dependency_links.txt
django_serializers.egg-info/top_level.txt
serializers/__init__.py
serializers/fields.py
serializers/fixture_serializer.py
serializers/parsers.py
serializers/renderers.py
serializers/serializer.py
serializers/tests.py
serializers/utils.py
serializers/compat/__init__.py
serializers/compat/json.py
serializers/compat/python.py
serializers/compat/xml.py
serializers/compat/yaml.py