Metadata-Version: 1.0
Name: django-serializers
Version: 0.6.0
Summary: Customizable serialization for Django
Home-page: http://github.com/tomchristie/django-serializers
Author: Tom Christie
Author-email: tom@tomchristie.com
License: BSD
Platform: UNKNOWN
